naturalsize/__init__.py
naturalsize-1.0.17.dist-info/licenses/LICENSE.txt
naturalsize-1.0.17.dist-info/METADATA
naturalsize-1.0.17.dist-info/WHEEL
naturalsize-1.0.17.dist-info/top_level.txt
naturalsize-1.0.17.dist-info/RECORD
