Metadata-Version: 2.4
Name: naturalsize
Version: 1.0.17
Summary: get human-readable size of files
Author-email: Leander Kafemann <leander@kafemann.berlin>
Project-URL: Homepage, https://github.com/LeanderKafemann/naturalsize
Classifier: Programming Language :: Python :: 3
Classifier: License :: OSI Approved :: MIT License
Classifier: Operating System :: OS Independent
Requires-Python: >=3.11
License-File: LICENSE.txt
Dynamic: license-file
